gujstemj/__init__.py
gujstemj/example.py
gujstemj/setup.py
gujstemj/stemmer.py
gujstemj-0.1.2.dist-info/licenses/LICENSE
gujstemj-0.1.2.dist-info/METADATA
gujstemj-0.1.2.dist-info/WHEEL
gujstemj-0.1.2.dist-info/top_level.txt
gujstemj-0.1.2.dist-info/RECORD
