Metadata-Version: 2.4
Name: gujstemj
Version: 0.1.2
Summary: A Python library for stemming Gujarati words.
Author-email: Jaideepsinh Raulji <jaideepraulji@gmail.com>
License: MIT License
Project-URL: Homepage, https://pypi.org/project/gujstemj/
Classifier: Programming Language :: Python :: 3
Classifier: License :: OSI Approved :: MIT License
Classifier: Operating System :: OS Independent
Classifier: Topic :: Text Processing :: Linguistic
Requires-Python: >=3.6
License-File: LICENSE
Dynamic: license-file
